bustracker/__init__.py
bustracker/base.py
bustracker/bus_tracker.py
bustracker-0.0.3.dist-info/LICENSE
bustracker-0.0.3.dist-info/METADATA
bustracker-0.0.3.dist-info/WHEEL
bustracker-0.0.3.dist-info/top_level.txt
bustracker-0.0.3.dist-info/RECORD
