Metadata-Version: 2.1
Name: bustracker
Version: 0.0.3
Summary: Get bus predictions from NextBus
Home-page: https://github.com/dalenguyen/bustracker
Author: Dale Nguyen
Author-email: dungnq@itbox4vn.com
License: UNKNOWN
Platform: UNKNOWN
Classifier: Programming Language :: Python :: 3
Classifier: License :: OSI Approved :: GNU General Public License v3 (GPLv3)
Classifier: Operating System :: OS Independent
Requires-Dist: requests
